metro_sp_mdp/__init__.py
metro_sp_mdp/__main__.py
metro_sp_mdp/hooks.py
metro_sp_mdp/pipeline_registry.py
metro_sp_mdp/settings.py
metro_sp_mdp/pipelines/__init__.py
metro_sp_mdp/pipelines/mdp/__init__.py
metro_sp_mdp/pipelines/mdp/nodes.py
metro_sp_mdp/pipelines/mdp/pipeline.py
tests/pipelines/__init__.py
tests/pipelines/mdp/__init__.py
tests/pipelines/mdp/test_pipeline.py
metro_sp_mdp-2.1.2.dist-info/METADATA
metro_sp_mdp-2.1.2.dist-info/WHEEL
metro_sp_mdp-2.1.2.dist-info/entry_points.txt
metro_sp_mdp-2.1.2.dist-info/top_level.txt
metro_sp_mdp-2.1.2.dist-info/RECORD
