Metadata-Version: 2.1
Name: metro-sp-mdp
Version: 2.1.2
Summary: UNKNOWN
Home-page: https://github.com/thiagodsd/metro-sp-mdp
Author: thiagodsd
Author-email: thiagodsd@thiagodsd.com
License: UNKNOWN
Platform: UNKNOWN
Requires-Dist: anyconfig (==0.10.1)
Requires-Dist: anyio (==3.5.0)
Requires-Dist: appdirs (==1.4.4)
Requires-Dist: argon2-cffi-bindings (==21.2.0)
Requires-Dist: argon2-cffi (==21.3.0)
Requires-Dist: arrow (==1.2.2)
Requires-Dist: attrs (==21.4.0)
Requires-Dist: babel (==2.9.1)
Requires-Dist: backcall (==0.2.0)
Requires-Dist: binaryornot (==0.4.4)
Requires-Dist: black (==21.5b1)
Requires-Dist: bleach (==4.1.0)
Requires-Dist: cachetools (==4.2.4)
Requires-Dist: certifi (==2021.10.8)
Requires-Dist: cffi (==1.15.0)
Requires-Dist: chardet (==4.0.0)
Requires-Dist: click (==7.1.2)
Requires-Dist: cookiecutter (==1.7.3)
Requires-Dist: coverage[toml] (==6.3.2)
Requires-Dist: cryptography (==36.0.1)
Requires-Dist: debugpy (==1.5.1)
Requires-Dist: decorator (==5.1.1)
Requires-Dist: defusedxml (==0.7.1)
Requires-Dist: dynaconf (==3.1.7)
Requires-Dist: entrypoints (==0.4)
Requires-Dist: flake8 (==3.9.2)
Requires-Dist: flask (==2.0.3)
Requires-Dist: fsspec (==2021.11.1)
Requires-Dist: gitdb (==4.0.9)
Requires-Dist: gitpython (==3.1.27)
Requires-Dist: idna (==2.10)
Requires-Dist: importlib-resources (==5.4.0)
Requires-Dist: iniconfig (==1.1.1)
Requires-Dist: ipykernel (==6.9.1)
Requires-Dist: ipython-genutils (==0.2.0)
Requires-Dist: ipython (==7.32.0)
Requires-Dist: ipywidgets (==7.6.5)
Requires-Dist: isort (==5.10.1)
Requires-Dist: itsdangerous (==2.1.0)
Requires-Dist: jedi (==0.18.1)
Requires-Dist: jinja2-time (==0.2.0)
Requires-Dist: jinja2 (==3.0.3)
Requires-Dist: jmespath (==0.10.0)
Requires-Dist: json5 (==0.9.6)
Requires-Dist: jsonschema (==4.4.0)
Requires-Dist: jupyter-client (==6.1.12)
Requires-Dist: jupyter-console (==6.4.0)
Requires-Dist: jupyter-core (==4.9.2)
Requires-Dist: jupyter-server (==1.13.5)
Requires-Dist: jupyter (==1.0.0)
Requires-Dist: jupyterlab-pygments (==0.1.2)
Requires-Dist: jupyterlab-server (==2.10.3)
Requires-Dist: jupyterlab-widgets (==1.0.2)
Requires-Dist: jupyterlab (==3.2.9)
Requires-Dist: kedro-telemetry (==0.1.3)
Requires-Dist: kedro (==0.17.6)
Requires-Dist: markupsafe (==2.1.0)
Requires-Dist: matplotlib-inline (==0.1.3)
Requires-Dist: mccabe (==0.6.1)
Requires-Dist: mistune (==0.8.4)
Requires-Dist: mypy-extensions (==0.4.3)
Requires-Dist: nbclassic (==0.3.5)
Requires-Dist: nbclient (==0.5.11)
Requires-Dist: nbconvert (==6.4.2)
Requires-Dist: nbformat (==5.1.3)
Requires-Dist: nbstripout (==0.5.0)
Requires-Dist: nest-asyncio (==1.5.4)
Requires-Dist: notebook (==6.4.8)
Requires-Dist: numpy (==1.22.2)
Requires-Dist: packaging (==21.3)
Requires-Dist: pandas (==1.4.1)
Requires-Dist: pandocfilters (==1.5.0)
Requires-Dist: parso (==0.8.3)
Requires-Dist: pathspec (==0.9.0)
Requires-Dist: pep517 (==0.12.0)
Requires-Dist: pexpect (==4.8.0)
Requires-Dist: pickleshare (==0.7.5)
Requires-Dist: pip-tools (==6.5.1)
Requires-Dist: pluggy (==0.13.1)
Requires-Dist: poyo (==0.5.0)
Requires-Dist: prometheus-client (==0.13.1)
Requires-Dist: prompt-toolkit (==3.0.28)
Requires-Dist: ptyprocess (==0.7.0)
Requires-Dist: py (==1.11.0)
Requires-Dist: pycodestyle (==2.7.0)
Requires-Dist: pycparser (==2.21)
Requires-Dist: pyflakes (==2.3.1)
Requires-Dist: pygments (==2.11.2)
Requires-Dist: pyopenssl (==22.0.0)
Requires-Dist: pyparsing (==3.0.7)
Requires-Dist: pyrsistent (==0.18.1)
Requires-Dist: pytest-cov (==3.0.0)
Requires-Dist: pytest-mock (==1.13.0)
Requires-Dist: pytest (==6.2.5)
Requires-Dist: python-dateutil (==2.8.2)
Requires-Dist: python-json-logger (==2.0.2)
Requires-Dist: python-slugify (==6.1.1)
Requires-Dist: pytz (==2021.3)
Requires-Dist: pyyaml (==5.4.1)
Requires-Dist: pyzmq (==22.3.0)
Requires-Dist: qtconsole (==5.2.2)
Requires-Dist: qtpy (==2.0.1)
Requires-Dist: regex (==2022.1.18)
Requires-Dist: requests (==2.25.1)
Requires-Dist: rope (==0.21.1)
Requires-Dist: send2trash (==1.8.0)
Requires-Dist: six (==1.16.0)
Requires-Dist: smmap (==5.0.0)
Requires-Dist: sniffio (==1.2.0)
Requires-Dist: terminado (==0.13.1)
Requires-Dist: testpath (==0.6.0)
Requires-Dist: text-unidecode (==1.3)
Requires-Dist: thefuzz (==0.19.0)
Requires-Dist: toml (==0.10.2)
Requires-Dist: tomli (==2.0.1)
Requires-Dist: toposort (==1.7)
Requires-Dist: tornado (==6.1)
Requires-Dist: traitlets (==5.1.1)
Requires-Dist: urllib3 (==1.26.8)
Requires-Dist: wcwidth (==0.2.5)
Requires-Dist: webencodings (==0.5.1)
Requires-Dist: websocket-client (==1.3.1)
Requires-Dist: werkzeug (==2.0.3)
Requires-Dist: wheel (==0.36.2)
Requires-Dist: widgetsnbextension (==3.5.2)
Requires-Dist: zipp (==3.7.0)
Provides-Extra: docs
Requires-Dist: docutils (<0.18.0) ; extra == 'docs'
Requires-Dist: ipykernel (<7.0,>=5.3) ; extra == 'docs'
Requires-Dist: nbsphinx (==0.8.1) ; extra == 'docs'
Requires-Dist: nbstripout (~=0.4) ; extra == 'docs'
Requires-Dist: recommonmark (==0.7.1) ; extra == 'docs'
Requires-Dist: sphinx-autodoc-typehints (==1.11.1) ; extra == 'docs'
Requires-Dist: sphinx-copybutton (==0.3.1) ; extra == 'docs'
Requires-Dist: sphinx-rtd-theme (==0.5.1) ; extra == 'docs'
Requires-Dist: sphinx (~=3.4.3) ; extra == 'docs'
